wink_sdk_affiliate_browse/__init__.py
wink_sdk_affiliate_browse/api_client.py
wink_sdk_affiliate_browse/api_response.py
wink_sdk_affiliate_browse/configuration.py
wink_sdk_affiliate_browse/exceptions.py
wink_sdk_affiliate_browse/py.typed
wink_sdk_affiliate_browse/rest.py
wink_sdk_affiliate_browse/api/__init__.py
wink_sdk_affiliate_browse/api/browse_api.py
wink_sdk_affiliate_browse/api/curated_list_api.py
wink_sdk_affiliate_browse/api/dynamic_list_api.py
wink_sdk_affiliate_browse/api/saved_search_api.py
wink_sdk_affiliate_browse/api/search_categories_api.py
wink_sdk_affiliate_browse/models/__init__.py
wink_sdk_affiliate_browse/models/add_static_list_item_request_affiliate.py
wink_sdk_affiliate_browse/models/add_static_list_supplier_request_affiliate.py
wink_sdk_affiliate_browse/models/add_static_seller_list_item_request_affiliate.py
wink_sdk_affiliate_browse/models/add_static_seller_list_supplier_request_affiliate.py
wink_sdk_affiliate_browse/models/address_affiliate.py
wink_sdk_affiliate_browse/models/boolean_response_affiliate.py
wink_sdk_affiliate_browse/models/contact_affiliate.py
wink_sdk_affiliate_browse/models/copy_move_static_list_item_request_affiliate.py
wink_sdk_affiliate_browse/models/copy_move_static_seller_list_item_request_affiliate.py
wink_sdk_affiliate_browse/models/country_affiliate.py
wink_sdk_affiliate_browse/models/create_static_list_and_add_item_request_affiliate.py
wink_sdk_affiliate_browse/models/create_static_list_and_add_supplier_request_affiliate.py
wink_sdk_affiliate_browse/models/create_static_seller_list_and_add_item_request_affiliate.py
wink_sdk_affiliate_browse/models/create_static_seller_list_and_add_supplier_request_affiliate.py
wink_sdk_affiliate_browse/models/custom_monetary_amount.py
wink_sdk_affiliate_browse/models/dynamic_list_affiliate.py
wink_sdk_affiliate_browse/models/dynamic_seller_list_affiliate.py
wink_sdk_affiliate_browse/models/dynamic_seller_list_request_affiliate.py
wink_sdk_affiliate_browse-0.0.57.dist-info/licenses/LICENSE
wink_sdk_affiliate_browse-0.0.57.dist-info/METADATA
wink_sdk_affiliate_browse-0.0.57.dist-info/WHEEL
wink_sdk_affiliate_browse-0.0.57.dist-info/top_level.txt
wink_sdk_affiliate_browse-0.0.57.dist-info/RECORD
